drx_protocol/__init__.py
drx_protocol/const.py
drx_protocol/exceptions.py
drx_protocol/protocol.py
drx_protocol/py.typed
drx_protocol/tcp.py
drx_protocol-1.0.4.dist-info/METADATA
drx_protocol-1.0.4.dist-info/WHEEL
drx_protocol-1.0.4.dist-info/top_level.txt
drx_protocol-1.0.4.dist-info/RECORD
